klabclient/__init__.py
klabclient/exceptions.py
klabclient/shell.py
klabclient/utils.py
klabclient/api/__init__.py
klabclient/api/app_tasks.py
klabclient/api/apps.py
klabclient/api/base.py
klabclient/api/charts.py
klabclient/api/client.py
klabclient/api/clusters.py
klabclient/api/datasets.py
klabclient/api/httpclient.py
klabclient/api/models.py
klabclient/api/organizations.py
klabclient/api/projects.py
klabclient/api/sharedclusters.py
klabclient/api/storage.py
klabclient/api/workspaces.py
klabclient/commands/__init__.py
klabclient/commands/app_tasks.py
klabclient/commands/apps.py
klabclient/commands/base.py
klabclient/commands/charts.py
klabclient/commands/clusters.py
klabclient/commands/datasets.py
klabclient/commands/models.py
klabclient/commands/organizations.py
klabclient/commands/projects.py
klabclient/commands/sharedclusters.py
klabclient/commands/storage.py
klabclient/commands/workspaces.py
klabclient/tests/__init__.py
klabclient/tests/unit/__init__.py
klabclient/tests/unit/base.py
klabclient/tests/unit/base_shell_test.py
klabclient/tests/unit/test_client.py
klabclient/tests/unit/test_httpclient.py
klabclient/tests/unit/test_shell.py
klabclient/tests/unit/test_utils.py
klabclient/tests/unit/resources/ctx.json
klabclient/tests/unit/tests/__init__.py
klabclient/tests/unit/tests/test_cli_bash_completion.py
klabclient/tests/unit/tests/test_cli_workspaces.py
klabclient/tests/unit/tests/test_workspaces.py
python_klabclient-1.0.4.dist-info/DESCRIPTION.rst
python_klabclient-1.0.4.dist-info/METADATA
python_klabclient-1.0.4.dist-info/RECORD
python_klabclient-1.0.4.dist-info/WHEEL
python_klabclient-1.0.4.dist-info/entry_points.txt
python_klabclient-1.0.4.dist-info/metadata.json
python_klabclient-1.0.4.dist-info/pbr.json
python_klabclient-1.0.4.dist-info/top_level.txt
