Metadata-Version: 2.0
Name: python-klabclient
Version: 1.0.4
Summary: Kuberlab API Client Library
Home-page: UNKNOWN
Author: Nikolay Makhotkin
Author-email: nikolay.makhotkin@gmail.com
License: Apache Software License
Platform: UNKNOWN
Classifier: Programming Language :: Python
Classifier: Programming Language :: Python :: 2
Classifier: Programming Language :: Python :: 2.7
Classifier: Programming Language :: Python :: 3
Classifier: Programming Language :: Python :: 3.5
Classifier: Intended Audience :: Information Technology
Classifier: Intended Audience :: System Administrators
Classifier: License :: OSI Approved :: Apache Software License
Classifier: Operating System :: POSIX :: Linux
Requires-Dist: PyYAML (>=3.10.0)
Requires-Dist: cliff (>=2.8.0)
Requires-Dist: oslo.utils (>=3.20.0)
Requires-Dist: pbr (!=2.1.0,>=2.0.0)
Requires-Dist: requests (>=2.14.2)
Requires-Dist: six (>=1.9.0)
